notifications_plugin/__init__.py
notifications_plugin/admin.py
notifications_plugin/apps.py
notifications_plugin/models.py
notifications_plugin/tests.py
notifications_plugin/views.py
notifications_plugin-0.1.1.dist-info/LICENSE
notifications_plugin-0.1.1.dist-info/METADATA
notifications_plugin-0.1.1.dist-info/WHEEL
notifications_plugin-0.1.1.dist-info/top_level.txt
notifications_plugin-0.1.1.dist-info/RECORD
