Metadata-Version: 2.1
Name: notifications-plugin
Version: 0.1.1
Summary: A django app to create simple notifications
Home-page: https://pypi.python.org/pypi/notifications-plugin/
Author: Aditya Palaparthy
Author-email: aditya94palaparthy@gmail.com
License: GNU General Public License v3.0
Platform: UNKNOWN
Classifier: Development Status :: 5 - Production/Stable
Classifier: Environment :: Web Environment
Classifier: Framework :: Django
Classifier: Intended Audience :: Developers
Classifier: License :: OSI Approved :: BSD License
Classifier: Operating System :: OS Independent
Classifier: Framework :: Django
Classifier: Framework :: Django :: 2.2
Classifier: Framework :: Django :: 3.0
Classifier: Programming Language :: Python
Classifier: Programming Language :: Python :: 3
Classifier: Programming Language :: Python :: 3.5
Classifier: Programming Language :: Python :: 3.6
Classifier: Programming Language :: Python :: 3.7
Classifier: Programming Language :: Python :: 3.8
Classifier: Topic :: Utilities
Requires-Python: >=3.1
Requires-Dist: django (>=2.2)
